pychrony/__init__.py
pychrony/exceptions.py
pychrony/models.py
pychrony/py.typed
pychrony/testing.py
pychrony/_core/__init__.py
pychrony/_core/_bindings.py
pychrony/_core/_build_bindings.py
pychrony/_core/_cffi_bindings.abi3.so
pychrony/_core/_fields.py
pychrony.libs/libchrony-efe7ecbc.so.0.0.1
pychrony-0.2.1.dist-info/METADATA
pychrony-0.2.1.dist-info/WHEEL
pychrony-0.2.1.dist-info/entry_points.txt
pychrony-0.2.1.dist-info/top_level.txt
pychrony-0.2.1.dist-info/RECORD
pychrony-0.2.1.dist-info/licenses/LICENSE
pychrony-0.2.1.dist-info/licenses/LICENSES/LGPL-2.1-or-later.txt
