Metadata-Version: 2.4
Name: pychrony
Version: 0.2.1
Summary: Python bindings for chrony NTP client
Author-email: arunderwood <arunderwood@users.noreply.github.com>
License-Expression: MIT AND LGPL-2.1-or-later
Project-URL: Homepage, https://github.com/arunderwood/pychrony
Project-URL: Documentation, https://pychrony.org/
Project-URL: Repository, https://github.com/arunderwood/pychrony.git
Project-URL: Issues, https://github.com/arunderwood/pychrony/issues
Classifier: Development Status :: 3 - Alpha
Classifier: Intended Audience :: Developers
Classifier: Intended Audience :: System Administrators
Classifier: Programming Language :: Python :: 3.10
Classifier: Programming Language :: Python :: 3.11
Classifier: Programming Language :: Python :: 3.12
Classifier: Programming Language :: Python :: 3.13
Classifier: Programming Language :: Python :: 3.14
Classifier: Topic :: System :: Networking :: Time Synchronization
Classifier: Topic :: Software Development :: Libraries :: Python Modules
Classifier: Operating System :: POSIX :: Linux
Requires-Python: >=3.10
License-File: LICENSE
License-File: LICENSES/LGPL-2.1-or-later.txt
Requires-Dist: cffi>=1.14.0
Dynamic: license-file
